LICENSE
MANIFEST.in
README.md
setup.cfg
setup.py
versioneer.py
smartfox/__init__.py
smartfox/_version.py
smartfox/constants.py
smartfox/smartfox.py
smartfox/smartfoxObjects.py
smartfox/valueMapping.py
smartfox.egg-info/PKG-INFO
smartfox.egg-info/SOURCES.txt
smartfox.egg-info/dependency_links.txt
smartfox.egg-info/requires.txt
smartfox.egg-info/top_level.txt